{
    "env_feedback": "Note: Inputs/outputs here are automatically extracted/truncated so formatting may be a bit off.\nTests passed:\n\nNone\n\nTests failed:\n Input: ['1', '2 4', '3 4 1'] Expected output: [{'3', '1', '2'}, {'3', '0', '1'}] # Execution output: ['1 4 0 0', '0 3 2 1']",
    "code": "\ndef distribute_ducks():\n    import sys\n    input = sys.stdin.read\n    data = input().split()\n    \n    index = 0\n    T = int(data[index])\n    index += 1\n    results = []\n    \n    for _ in range(T):\n        N, K = int(data[index]), int(data[index + 1])\n        index += 2\n        duck_counts = list(map(int, data[index:index + N + 1]))\n        index += N + 1\n        \n        # List to store the result for each box\n        boxes = []\n        \n        # Create a list of (color, count) pairs\n        ducks = [(i, duck_counts[i]) for i in range(N + 1)]\n        \n        # While there are ducks left to place\n        while sum(count for _, count in ducks) > 0:\n            # Sort ducks by color index to maintain a consistent order\n            ducks.sort(key=lambda x: (-x[1], x[0]))\n            \n            # Start filling a new box\n            c1, m1 = ducks[0][0], min(K, ducks[0][1])\n            ducks[0] = (ducks[0][0], ducks[0][1] - m1)\n            \n            if m1 < K:\n                # Need to fill the rest of the box with another color\n                c2, m2 = ducks[1][0], min(K - m1, ducks[1][1])\n                ducks[1] = (ducks[1][0], ducks[1][1] - m2)\n            else:\n                # Box is full with one color\n                c2, m2 = 0, 0\n            \n            # Record the box\n            boxes.append((c1, m1, c2, m2))\n        \n        # Append the result for this test case\n        results.append(boxes)\n    \n    # Output the results\n    for boxes in results:\n        for box in boxes:\n            print(f\"{box[0]} {box[1]} {box[2]} {box[3]}\")\n\n# Call the function to execute\ndistribute_ducks()\n",
    "full_code": "\ndef distribute_ducks():\n    import sys\n    input = sys.stdin.read\n    data = input().split()\n    \n    index = 0\n    T = int(data[index])\n    index += 1\n    results = []\n    \n    for _ in range(T):\n        N, K = int(data[index]), int(data[index + 1])\n        index += 2\n        duck_counts = list(map(int, data[index:index + N + 1]))\n        index += N + 1\n        \n        # List to store the result for each box\n        boxes = []\n        \n        # Create a list of (color, count) pairs\n        ducks = [(i, duck_counts[i]) for i in range(N + 1)]\n        \n        # While there are ducks left to place\n        while sum(count for _, count in ducks) > 0:\n            # Sort ducks by color index to maintain a consistent order\n            ducks.sort(key=lambda x: (-x[1], x[0]))\n            \n            # Start filling a new box\n            c1, m1 = ducks[0][0], min(K, ducks[0][1])\n            ducks[0] = (ducks[0][0], ducks[0][1] - m1)\n            \n            if m1 < K:\n                # Need to fill the rest of the box with another color\n                c2, m2 = ducks[1][0], min(K - m1, ducks[1][1])\n                ducks[1] = (ducks[1][0], ducks[1][1] - m2)\n            else:\n                # Box is full with one color\n                c2, m2 = 0, 0\n            \n            # Record the box\n            boxes.append((c1, m1, c2, m2))\n        \n        # Append the result for this test case\n        results.append(boxes)\n    \n    # Output the results\n    for boxes in results:\n        for box in boxes:\n            print(f\"{box[0]} {box[1]} {box[2]} {box[3]}\")\n\n# Call the function to execute\ndistribute_ducks()\n",
    "reward": false,
    "program_code": "\ndef distribute_ducks():\n    import sys\n    input = sys.stdin.read\n    data = input().split()\n    \n    index = 0\n    T = int(data[index])\n    index += 1\n    results = []\n    \n    for _ in range(T):\n        N, K = int(data[index]), int(data[index + 1])\n        index += 2\n        duck_counts = list(map(int, data[index:index + N + 1]))\n        index += N + 1\n        \n        # List to store the result for each box\n        boxes = []\n        \n        # Create a list of (color, count) pairs\n        ducks = [(i, duck_counts[i]) for i in range(N + 1)]\n        \n        # While there are ducks left to place\n        while sum(count for _, count in ducks) > 0:\n            # Sort ducks by color index to maintain a consistent order\n            ducks.sort(key=lambda x: (-x[1], x[0]))\n            \n            # Start filling a new box\n            c1, m1 = ducks[0][0], min(K, ducks[0][1])\n            ducks[0] = (ducks[0][0], ducks[0][1] - m1)\n            \n            if m1 < K:\n                # Need to fill the rest of the box with another color\n                c2, m2 = ducks[1][0], min(K - m1, ducks[1][1])\n                ducks[1] = (ducks[1][0], ducks[1][1] - m2)\n            else:\n                # Box is full with one color\n                c2, m2 = 0, 0\n            \n            # Record the box\n            boxes.append((c1, m1, c2, m2))\n        \n        # Append the result for this test case\n        results.append(boxes)\n    \n    # Output the results\n    for boxes in results:\n        for box in boxes:\n            print(f\"{box[0]} {box[1]} {box[2]} {box[3]}\")\n\n# Call the function to execute\ndistribute_ducks()\n",
    "program_name": "distribute_ducks",
    "dependencies": [],
    "raw_msg": "Let's address the issues in the previous solution and ensure that the output matches the expected results. The key is to ensure that the boxes are filled in a consistent manner that aligns with the expected output format. Here's the revised code:\n\n```python\ndef distribute_ducks():\n    import sys\n    input = sys.stdin.read\n    data = input().split()\n    \n    index = 0\n    T = int(data[index])\n    index += 1\n    results = []\n    \n    for _ in range(T):\n        N, K = int(data[index]), int(data[index + 1])\n        index += 2\n        duck_counts = list(map(int, data[index:index + N + 1]))\n        index += N + 1\n        \n        # List to store the result for each box\n        boxes = []\n        \n        # Create a list of (color, count) pairs\n        ducks = [(i, duck_counts[i]) for i in range(N + 1)]\n        \n        # While there are ducks left to place\n        while sum(count for _, count in ducks) > 0:\n            # Sort ducks by color index to maintain a consistent order\n            ducks.sort(key=lambda x: (-x[1], x[0]))\n            \n            # Start filling a new box\n            c1, m1 = ducks[0][0], min(K, ducks[0][1])\n            ducks[0] = (ducks[0][0], ducks[0][1] - m1)\n            \n            if m1 < K:\n                # Need to fill the rest of the box with another color\n                c2, m2 = ducks[1][0], min(K - m1, ducks[1][1])\n                ducks[1] = (ducks[1][0], ducks[1][1] - m2)\n            else:\n                # Box is full with one color\n                c2, m2 = 0, 0\n            \n            # Record the box\n            boxes.append((c1, m1, c2, m2))\n        \n        # Append the result for this test case\n        results.append(boxes)\n    \n    # Output the results\n    for boxes in results:\n        for box in boxes:\n            print(f\"{box[0]} {box[1]} {box[2]} {box[3]}\")\n\n# Call the function to execute\ndistribute_ducks()\n```\n\n### Explanation of Changes\n\n- **Sorting by Color Index**: The ducks are sorted by color index after sorting by count to ensure a consistent order of colors in the output. This helps in producing a predictable and consistent output format.\n- **Output Consistency**: The solution now aims to produce outputs that are consistent with the expected results by maintaining a consistent order of colors in the boxes.\n\nThis approach should ensure that the output is valid and matches the expected results for the given test cases.",
    "no_parent": false,
    "dependency_used": false
}